FacebookPagePoster/FacebookPagePoster.py
FacebookPagePoster/__init__.py
FacebookPagePoster-0.1.8.dist-info/LICENSE
FacebookPagePoster-0.1.8.dist-info/METADATA
FacebookPagePoster-0.1.8.dist-info/WHEEL
FacebookPagePoster-0.1.8.dist-info/top_level.txt
FacebookPagePoster-0.1.8.dist-info/RECORD
